adafruit_lsm303dlh_mag.py
adafruit_circuitpython_lsm303dlh_mag-1.1.26.dist-info/licenses/LICENSE
adafruit_circuitpython_lsm303dlh_mag-1.1.26.dist-info/METADATA
adafruit_circuitpython_lsm303dlh_mag-1.1.26.dist-info/WHEEL
adafruit_circuitpython_lsm303dlh_mag-1.1.26.dist-info/top_level.txt
adafruit_circuitpython_lsm303dlh_mag-1.1.26.dist-info/RECORD
